hypnotoad/__init__.py
hypnotoad/__version__.py
hypnotoad/cases/__init__.py
hypnotoad/cases/circular.py
hypnotoad/cases/tokamak.py
hypnotoad/cases/torpex.py
hypnotoad/core/__init__.py
hypnotoad/core/equilibrium.py
hypnotoad/core/mesh.py
hypnotoad/core/multilocationarray.py
hypnotoad/geqdsk/__init__.py
hypnotoad/geqdsk/_fileutils.py
hypnotoad/geqdsk/_geqdsk.py
hypnotoad/gui/__init__.py
hypnotoad/gui/__main__.py
hypnotoad/gui/gui.py
hypnotoad/gui/hypnotoad_mainWindow.py
hypnotoad/gui/hypnotoad_preferences.py
hypnotoad/gui/matplotlib_widget.py
hypnotoad/scripts/__init__.py
hypnotoad/scripts/hypnotoad_circular.py
hypnotoad/scripts/hypnotoad_geqdsk.py
hypnotoad/scripts/hypnotoad_get_flux_surfaces.py
hypnotoad/scripts/hypnotoad_plot_equilibrium.py
hypnotoad/scripts/hypnotoad_plot_grid_cells.py
hypnotoad/scripts/hypnotoad_recreate_inputs.py
hypnotoad/scripts/hypnotoad_torpex.py
hypnotoad/test_suite/__init__.py
hypnotoad/test_suite/test_circular.py
hypnotoad/test_suite/test_critical.py
hypnotoad/test_suite/test_dct.py
hypnotoad/test_suite/test_equilibrium.py
hypnotoad/test_suite/test_fileutils.py
hypnotoad/test_suite/test_geqdsk.py
hypnotoad/test_suite/test_mesh.py
hypnotoad/test_suite/test_polygons.py
hypnotoad/test_suite/test_tokamak.py
hypnotoad/test_suite/test_torpex.py
hypnotoad/test_suite/test_utils.py
hypnotoad/test_suite/test_versioning.py
hypnotoad/test_suite/utils_for_tests.py
hypnotoad/utils/__init__.py
hypnotoad/utils/critical.py
hypnotoad/utils/dct_interpolation.py
hypnotoad/utils/parallel_map.py
hypnotoad/utils/polygons.py
hypnotoad/utils/utils.py
hypnotoad-0.5.2.dist-info/LICENCE
hypnotoad-0.5.2.dist-info/METADATA
hypnotoad-0.5.2.dist-info/WHEEL
hypnotoad-0.5.2.dist-info/entry_points.txt
hypnotoad-0.5.2.dist-info/top_level.txt
hypnotoad-0.5.2.dist-info/RECORD
