Metadata-Version: 2.1
Name: hypnotoad
Version: 0.5.2
Summary: Grid generator for BOUT++
Author: Ben Dudson, BOUT++ team
Author-email: John Omotani <john.omotani@ukaea.uk>
License: GNU GENERAL PUBLIC LICENSE
Project-URL: Source, https://github.com/boutproject/hypnotoad
Project-URL: Tracker, https://github.com/boutproject/hypnotoad/issues
Project-URL: Documentation, https://hypnotoad.readthedocs.io/en/latest/
Keywords: gyrokinetics,analysis,plasma,research
Classifier: Programming Language :: Python :: 3
Classifier: License :: OSI Approved :: GNU General Public License v3 or later (GPLv3+)
Classifier: Operating System :: OS Independent
Requires-Python: >=3.8
License-File: LICENCE
Requires-Dist: boututils (~=0.1.7)
Requires-Dist: dill (!=0.3.5,!=0.3.5.1,~=0.3)
Requires-Dist: func-timeout (~=4.3)
Requires-Dist: matplotlib (~=3.2)
Requires-Dist: netCDF4 (~=1.5)
Requires-Dist: numpy (~=1.18)
Requires-Dist: optionsfactory (~=1.0.11)
Requires-Dist: PyYAML (>=5.1)
Requires-Dist: scipy (~=1.6)
Requires-Dist: Qt.py (~=1.2)
Provides-Extra: docs
Requires-Dist: sphinx (~=5.3.0) ; extra == 'docs'
Requires-Dist: myst-parser (~=0.18.1) ; extra == 'docs'
Requires-Dist: sphinx-argparse (~=0.3.1) ; extra == 'docs'
Requires-Dist: sphinx-rtd-theme (~=1.1.1) ; extra == 'docs'
Requires-Dist: texttable (~=1.6.7) ; extra == 'docs'
Provides-Extra: gui-pyqt5
Requires-Dist: PyQt5 (~=5.12) ; extra == 'gui-pyqt5'
Provides-Extra: gui-pyside
Requires-Dist: pyside2 (~=5.13) ; extra == 'gui-pyside'
Provides-Extra: tests
Requires-Dist: pytest (>=3.3.0) ; extra == 'tests'
